vessel/__init__.py
vessel/_helpers.py
vessel/_instance.py
vessel/_manage.py
vessel-4.2.0.dist-info/METADATA
vessel-4.2.0.dist-info/WHEEL
vessel-4.2.0.dist-info/top_level.txt
vessel-4.2.0.dist-info/RECORD
